scanc/__init__.py
scanc/cli.py
scanc/core.py
scanc/formatter.py
scanc/token_counter.py
scanc/tree.py
scanc-1.2.2.dist-info/licenses/LICENCE
scanc-1.2.2.dist-info/METADATA
scanc-1.2.2.dist-info/WHEEL
scanc-1.2.2.dist-info/entry_points.txt
scanc-1.2.2.dist-info/top_level.txt
scanc-1.2.2.dist-info/RECORD
