Metadata-Version: 2.4
Name: scanc
Version: 1.2.2
Summary: AI-ready code-base scanner that outputs Markdown or XML.
Home-page: https://github.com/mqxym/scanc
Author: mqxym
Author-email: maxim@omg.lol
License: MIT
Project-URL: Source, https://github.com/mqxym/scanc
Project-URL: Bug Tracker, https://github.com/mqxym/scanc/issues
Classifier: Programming Language :: Python :: 3
Classifier: Programming Language :: Python :: 3.9
Classifier: Programming Language :: Python :: 3.10
Classifier: Programming Language :: Python :: 3.11
Classifier: Programming Language :: Python :: 3.12
Classifier: License :: OSI Approved :: MIT License
Classifier: Operating System :: OS Independent
Classifier: Environment :: Console
Classifier: Topic :: Software Development :: Code Generators
Classifier: Topic :: Software Development :: Documentation
Requires-Python: >=3.9
License-File: LICENCE
Requires-Dist: click>=8.0
Requires-Dist: treelib>=1.6.1
Provides-Extra: dev
Requires-Dist: pytest; extra == "dev"
Requires-Dist: tox; extra == "dev"
Provides-Extra: tiktoken
Requires-Dist: tiktoken>=0.7; extra == "tiktoken"
Dynamic: author
Dynamic: author-email
Dynamic: classifier
Dynamic: description
Dynamic: description-content-type
Dynamic: home-page
Dynamic: license
Dynamic: license-file
Dynamic: project-url
Dynamic: provides-extra
Dynamic: requires-dist
Dynamic: requires-python
Dynamic: summary
